coloring/__init__.py
coloring/__main__.py
coloring/automatic_generated_convenience_functions.py
coloring/coloring.py
coloring/consts.py
coloring/convenience_functions.py
coloring/demo.py
coloring/initialize.py
coloring/remove_graphics.py
coloring/cli/__init__.py
coloring/cli/cli.py
coloring/cli/subcmdparse.py
coloring-0.1.8.dist-info/LICENSE
coloring-0.1.8.dist-info/METADATA
coloring-0.1.8.dist-info/WHEEL
coloring-0.1.8.dist-info/entry_points.txt
coloring-0.1.8.dist-info/top_level.txt
coloring-0.1.8.dist-info/RECORD
